chirpy/__init__.py
chirpy/prob_phenom_model/__init__.py
chirpy/prob_phenom_model/collocation.py
chirpy/prob_phenom_model/pn.py
chirpy/prob_phenom_model/ppm_utils.py
chirpy/prob_phenom_model/workflow_utils.py
gw_chirpy-0.0.5.dist-info/LICENSE
gw_chirpy-0.0.5.dist-info/METADATA
gw_chirpy-0.0.5.dist-info/WHEEL
gw_chirpy-0.0.5.dist-info/top_level.txt
gw_chirpy-0.0.5.dist-info/RECORD
