Metadata-Version: 2.1
Name: gw_chirpy
Version: 0.0.5
Home-page: https://gitlab.com/SpaceTimeKhantinuum/chirpy
Author: Sebastian Khan
Author-email: Sebastian Khan <sebastiank17@gmail.com>
License-File: LICENSE
Requires-Dist: numpy
Requires-Dist: scipy
Requires-Dist: sympy
Requires-Dist: gw-phenom
Requires-Dist: pandas ==1.5.1
Requires-Dist: cloudpickle
Requires-Dist: lalsuite
Requires-Dist: pycbc
Requires-Dist: scikit-learn
Requires-Dist: matplotlib
Requires-Dist: jupyterlab
